demosaicnet/__init__.py
demosaicnet/dataset.py
demosaicnet/modules.py
demosaicnet/mosaic.py
demosaicnet/utils.py
demosaicnet/version.py
demosaicnet/data/bayer.pth
demosaicnet/data/test_input.png
demosaicnet/data/xtrans.pth
demosaicnet-0.0.14.data/scripts/demosaicnet_demo
demosaicnet-0.0.14.data/scripts/demosaicnet_demo.py
demosaicnet-0.0.14.dist-info/LICENSE
demosaicnet-0.0.14.dist-info/METADATA
demosaicnet-0.0.14.dist-info/WHEEL
demosaicnet-0.0.14.dist-info/top_level.txt
demosaicnet-0.0.14.dist-info/RECORD
