Metadata-Version: 2.1
Name: demosaicnet
Version: 0.0.14
Summary: Minimal implementation of Deep Joint Demosaicking and Denoising [Gharbi2016]
Home-page: https://github.com/mgharbi/
Author: Michaël Gharbi
Author-email: gharbi@csail.mit.edu
License: UNKNOWN
Platform: UNKNOWN
Classifier: Programming Language :: Python :: 3
Classifier: License :: OSI Approved :: MIT License
Classifier: Operating System :: MacOS :: MacOS X
Classifier: Operating System :: POSIX
Requires-Dist: wget
Requires-Dist: tqdm
Requires-Dist: torch
Requires-Dist: imageio
Requires-Dist: numpy
